autoschema/__init__.py
autoschema/main.py
autoschema_harshitajain123-0.1.0.dist-info/METADATA
autoschema_harshitajain123-0.1.0.dist-info/WHEEL
autoschema_harshitajain123-0.1.0.dist-info/entry_points.txt
autoschema_harshitajain123-0.1.0.dist-info/license
autoschema_harshitajain123-0.1.0.dist-info/top_level.txt
autoschema_harshitajain123-0.1.0.dist-info/RECORD
