Metadata-Version: 2.1
Name: autoschema-harshitajain123
Version: 0.1.0
Summary: A package that automates schema migrations by comparing schemas and generating migration scripts.
Author: Harshita Jain
License-File: license
Requires-Dist: SQLAlchemy
